webssh/__init__.py
webssh/_version.py
webssh/handler.py
webssh/main.py
webssh/policy.py
webssh/settings.py
webssh/utils.py
webssh/vault.py
webssh/worker.py
webssh/static/css/bootstrap.min.css
webssh/static/css/fullscreen.min.css
webssh/static/css/xterm.min.css
webssh/static/css/fonts/.gitignore
webssh/static/img/favicon.png
webssh/static/js/bootstrap.min.js
webssh/static/js/jquery.min.js
webssh/static/js/main.js
webssh/static/js/popper.min.js
webssh/static/js/xterm-addon-fit.min.js
webssh/static/js/xterm.min.js
webssh/templates/index.html
webssh/vault-certs/token.json
webssh/vault-certs/vaultcert.crt
webssh/vault-certs/vaultcert.key
webssh/vault-certs/vaultcert.pem
dc_webssh-1.0.0.dist-info/LICENSE
dc_webssh-1.0.0.dist-info/METADATA
dc_webssh-1.0.0.dist-info/WHEEL
dc_webssh-1.0.0.dist-info/entry_points.txt
dc_webssh-1.0.0.dist-info/top_level.txt
dc_webssh-1.0.0.dist-info/RECORD
