Metadata-Version: 2.1
Name: dc-webssh
Version: 1.0.0
Summary: Web based ssh client for DC-bench
Home-page: https://github.com/kkumarM/webssh
Author: Karthik Kumaar
Author-email: karthikkumar.m@gmail.com
License: MIT
Platform: UNKNOWN
Classifier: Programming Language :: Python
Classifier: Programming Language :: Python :: 2
Classifier: Programming Language :: Python :: 2.7
Classifier: Programming Language :: Python :: 3
Classifier: Programming Language :: Python :: 3.4
Classifier: Programming Language :: Python :: 3.5
Classifier: Programming Language :: Python :: 3.6
Classifier: Programming Language :: Python :: 3.7
Classifier: Programming Language :: Python :: 3.8
Classifier: Programming Language :: Python :: 3.9
License-File: LICENSE
Requires-Dist: tornado (>=4.5.0)
Requires-Dist: paramiko (>=2.3.1)
